[
    {
      "model": "pittyapi.adopter",
      "pk": 1,
      "fields": {
        "first_name": "John",
        "last_name": "Doe",
        "email": "john.doe@example.com",
        "user_id": 1
      }
    },
    {
      "model": "pittyapi.adopter",
      "pk": 2,
      "fields": {
        "first_name": "Meg",
        "last_name": "Ducharme",
        "email": "meg@ducharme.com",
        "user_id": 2
      }
    },
    {
      "model": "pittyapi.adopter",
      "pk": 3,
      "fields": {
        "first_name": "Jenna",
        "last_name": "Solis",
        "email": "jenna@solis.com",
        "user_id": 3
      }
    },
    {
      "model": "pittyapi.adopter",
      "pk": 4,
      "fields": {
        "first_name": "Bryan",
        "last_name": "Nilson",
        "email": "bryan@nilson.com",
        "user_id": 4
      }
    },
    {
      "model": "pittyapi.adopter",
      "pk": 5,
      "fields": {
        "first_name": "Emily",
        "last_name": "Lemmon",
        "email": "emily@lemmon.com",
        "user_id": 5
      }
    }
  ]